plastburstalign/__init__.py
plastburstalign/__main__.py
plastburstalign/alignment_ops.py
plastburstalign/extraction_ops.py
plastburstalign/helpers.py
plastburstalign/logging_ops.py
plastburstalign/plastome_burst_and_align.py
plastburstalign/seqfeature_ops.py
plastburstalign/user_parameters.py
plastburstalign-0.9.1.dist-info/LICENSE
plastburstalign-0.9.1.dist-info/METADATA
plastburstalign-0.9.1.dist-info/WHEEL
plastburstalign-0.9.1.dist-info/top_level.txt
plastburstalign-0.9.1.dist-info/RECORD
