Metadata-Version: 2.1
Name: plastburstalign
Version: 0.9.1
Summary: A Python tool to extract and align genes, introns, and intergenic spacers across hundreds of plastid genomes using associative arrays
Author-email: "Michael Gruenstaeudl, PhD" <m_gruenstaeudl@fhsu.edu>, Gregory Smith <g_smith10@mail.fhsu.edu>
Project-URL: Homepage, https://gruenstaeudl-lab.com/
Project-URL: Repository, https://github.com/michaelgruenstaeudl/PlastomeBurstAndAlign
Keywords: bioinformatics,alignment,flatfile,MAFFT
Classifier: Development Status :: 3 - Alpha
Classifier: License :: OSI Approved :: BSD License
Classifier: Programming Language :: Python :: 3.9
Classifier: Programming Language :: Python :: 3.10
Classifier: Programming Language :: Python :: 3.11
Classifier: Programming Language :: Python :: 3.12
Classifier: Intended Audience :: Science/Research
Classifier: Intended Audience :: Developers
Classifier: Topic :: Scientific/Engineering :: Bio-Informatics
Requires-Python: >=3.9
License-File: LICENSE
Requires-Dist: biopython>=1.78
Requires-Dist: coloredlogs>=14.0
Requires-Dist: requests
